ablang/__init__.py
ablang/embedding.py
ablang/encoderblocks.py
ablang/extra_fns.py
ablang/fairseq_mha.py
ablang/model.py
ablang/pretrained.py
ablang/tokenizers.py
ablang-0.3.1.dist-info/LICENSE
ablang-0.3.1.dist-info/METADATA
ablang-0.3.1.dist-info/WHEEL
ablang-0.3.1.dist-info/top_level.txt
ablang-0.3.1.dist-info/RECORD
