Metadata-Version: 2.1
Name: ablang
Version: 0.3.1
Summary: AbLang: A language model for antibodies.
Maintainer: Tobias Hegelund Olsen
Maintainer-email: tobias.olsen@stats.ox.ac.uk
License: BSD 3-clause license
License-File: LICENSE
Requires-Dist: requests
Requires-Dist: torch >=1.6
Requires-Dist: numpy
Requires-Dist: pandas
Requires-Dist: numba
